MANIFEST.in
README.markdown
setup.py
dotfilemanager/__init__.py
dotfilemanager/dotfilemanager.py
dotfilemanager.egg-info/PKG-INFO
dotfilemanager.egg-info/SOURCES.txt
dotfilemanager.egg-info/dependency_links.txt
dotfilemanager.egg-info/entry_points.txt
dotfilemanager.egg-info/top_level.txt