Metadata-Version: 1.1
Name: dotfilemanager
Version: 1.0.0
Summary: A dotfiles manager script
Home-page: https://github.com/seanh/dotfilemanager
Author: Sean Hammond
Author-email: dotfilemanager@seanh.cc
License: GPLv3
Platform: UNKNOWN
Classifier: Development Status :: 4 - Beta
Classifier: License :: OSI Approved :: GNU General Public License v3 (GPLv3)
Classifier: Programming Language :: Python :: 2.7
